Metadata-Version: 2.1
Name: trf-dgraham
Version: 0.0.23
Summary: This is a simple application for recording the sequence of occasions on which a task is completed and forecasting when the next completion might be needed.
Home-page: https://github.com/dagraham/trf-dgraham
Author: Daniel A Graham
Author-email: dnlgrhm@gmail.com
Classifier: Programming Language :: Python :: 3
Classifier: License :: OSI Approved :: MIT License
Classifier: Operating System :: OS Independent
Requires-Python: >=3.9.0
Requires-Dist: prompt-toolkit>=3.0.24
Requires-Dist: ruamel.yaml>=0.15.88
Requires-Dist: python-dateutil>=2.7.3
Requires-Dist: persistent>=4.6.4
Requires-Dist: ZODB>=5.6.0
Requires-Dist: transaction>=3.0.1
Requires-Dist: lorem>=0.1.1
Requires-Dist: pyperclip>=1.7.0
